cypocketfft/fft.cpython-38-x86_64-linux-gnu.so
cypocketfft/wrapper.c
cypocketfft/plancache.cpp
cypocketfft/__init__.pxd
cypocketfft/wrapper.pxd
cypocketfft/wrapper.cpython-38-x86_64-linux-gnu.so
cypocketfft/fft.cpp
cypocketfft/fft.pxd
cypocketfft/fft.pyx
cypocketfft/plancache.pxd
cypocketfft/plancache.pyx
cypocketfft/__init__.py
cypocketfft/plancache.cpython-38-x86_64-linux-gnu.so
cypocketfft/wrapper.pyx
cypocketfft/_pocketfft_lib/pocketfft.h
cypocketfft/_pocketfft_lib/LICENSE.md
cypocketfft/_pocketfft_lib/README.md
cypocketfft/_pocketfft_lib/pocketfft.c
cypocketfft/_pocketfft_lib/__init__.py
cypocketfft/_pocketfft_lib/pocketfft_numpy.c
cypocketfft/_pocketfft_lib/ffttest.c
cython_pocketfft-0.0.12.dist-info/top_level.txt
cython_pocketfft-0.0.12.dist-info/LICENSE
cython_pocketfft-0.0.12.dist-info/WHEEL
cython_pocketfft-0.0.12.dist-info/METADATA
cython_pocketfft-0.0.12.dist-info/RECORD
